examples/__init__.py
examples/mailgun.py
examples/smtp.py
fluentmail/__init__.py
fluentmail/message.py
fluentmail/utils.py
fluentmail/backends/__init__.py
fluentmail/backends/base.py
fluentmail/backends/mailgun.py
fluentmail/backends/smtp.py
fluentmail-1.0.0.dist-info/LICENSE
fluentmail-1.0.0.dist-info/METADATA
fluentmail-1.0.0.dist-info/WHEEL
fluentmail-1.0.0.dist-info/top_level.txt
fluentmail-1.0.0.dist-info/RECORD
