Metadata-Version: 2.1
Name: fluentmail
Version: 1.0.0
Summary: Tiny library to send email
Home-page: https://github.com/alexandrevicenzi/fluentmail
Author: Alexandre Vicenzi
Author-email: pypi@alxd.me
Maintainer: Alexandre Vicenzi
Maintainer-email: pypi@alxd.me
License: MIT
Keywords: python,email,mail,smtp,mailgun
Platform: 
Classifier: Development Status :: 5 - Production/Stable
Classifier: Programming Language :: Python
Classifier: Programming Language :: Python :: 2
Classifier: Programming Language :: Python :: 2.6
Classifier: Programming Language :: Python :: 2.7
Classifier: Programming Language :: Python :: 3
Classifier: Programming Language :: Python :: 3.4
Classifier: Programming Language :: Python :: 3.5
Classifier: Programming Language :: Python :: 3.6
Classifier: Programming Language :: Python :: 3.7
Classifier: License :: OSI Approved :: MIT License
Classifier: Operating System :: MacOS
Classifier: Operating System :: Microsoft
Classifier: Operating System :: POSIX
Classifier: Operating System :: Unix
Classifier: Topic :: Communications :: Email
Classifier: Topic :: Utilities
